century/__init__.py
Century-0.0.1.dist-info/METADATA
Century-0.0.1.dist-info/WHEEL
Century-0.0.1.dist-info/top_level.txt
Century-0.0.1.dist-info/RECORD
